[
  {
    "name": "aaa",
    "requester": "edude15000",
    "requesterIsHere": "[IN CHAT]",
    "level": "$$$",
    "youtubeLink": "http://www.youtube.com/watch?v=fnCjUsc7y2M",
    "youtubeTitle": "AAA - The AAA Girls feat. Alaska Thunderfuck, Willam and Courtney Act",
    "durationInSeconds": 225,
    "index": 1,
    "tuning": "",
    "customsForgeLink": "",
    "parts": "",
    "dlcCreator": "",
    "formattedDuration": "00:03:45",
    "officialSong": false,
    "cfSongName": "",
    "cfSongArtist": "aaa",
    "cfAlbum": ""
  },
  {
    "name": "bbb",
    "requester": "edude15000",
    "requesterIsHere": "[IN CHAT]",
    "level": "VIP",
    "youtubeLink": "http://www.youtube.com/watch?v=uUHftaxKjKk",
    "youtubeTitle": "Lonzo Ball - BBB (Official Music Video)",
    "durationInSeconds": 210,
    "index": 2,
    "tuning": "",
    "customsForgeLink": "",
    "parts": "",
    "dlcCreator": "",
    "formattedDuration": "00:03:30",
    "officialSong": false,
    "cfSongName": "",
    "cfSongArtist": "bbb",
    "cfAlbum": ""
  },
  {
    "name": "ddd",
    "requester": "edude15000",
    "requesterIsHere": "[IN CHAT]",
    "level": "",
    "youtubeLink": "http://www.youtube.com/watch?v=axVvZrDz60k",
    "youtubeTitle": "[EXID(이엑스아이디)] 덜덜덜(DDD) 뮤직 비디오 (Official Music Video)",
    "durationInSeconds": 207,
    "index": 3,
    "tuning": "",
    "customsForgeLink": "",
    "parts": "",
    "dlcCreator": "",
    "formattedDuration": "00:03:27",
    "officialSong": false,
    "cfSongName": "",
    "cfSongArtist": "ddd",
    "cfAlbum": ""
  },
  {
    "name": "eee",
    "requester": "edude15000",
    "requesterIsHere": "[IN CHAT]",
    "level": "",
    "youtubeLink": "http://www.youtube.com/watch?v=XlhKQKb30xY",
    "youtubeTitle": "Extraordinarily Excellent Entities Episode 4: EEE = mc^2",
    "durationInSeconds": 834,
    "index": 4,
    "tuning": "",
    "customsForgeLink": "",
    "parts": "",
    "dlcCreator": "",
    "formattedDuration": "00:13:54",
    "officialSong": false,
    "cfSongName": "",
    "cfSongArtist": "eee",
    "cfAlbum": ""
  },
  {
    "name": "ppp",
    "requester": "edude15000",
    "requesterIsHere": "[IN CHAT]",
    "level": "",
    "youtubeLink": "http://www.youtube.com/watch?v=NFhJRTdmviA",
    "youtubeTitle": "Beach House - PPP",
    "durationInSeconds": 369,
    "index": 5,
    "tuning": "",
    "customsForgeLink": "",
    "parts": "",
    "dlcCreator": "",
    "formattedDuration": "00:06:09",
    "officialSong": false,
    "cfSongName": "",
    "cfSongArtist": "ppp",
    "cfAlbum": ""
  },
  {
    "name": "alalalalalalalvallavla",
    "requester": "edude15000",
    "requesterIsHere": "[IN CHAT]",
    "level": "",
    "youtubeLink": "",
    "youtubeTitle": "",
    "durationInSeconds": 0,
    "index": 6,
    "tuning": "",
    "customsForgeLink": "",
    "parts": "",
    "dlcCreator": "",
    "formattedDuration": "~00:04:00",
    "officialSong": false,
    "cfSongName": "",
    "cfSongArtist": "alalalalalalalvallavla",
    "cfAlbum": ""
  }
]